Metadata-Version: 1.0
Name: mypackjcal
Version: 0.0.1
Summary: this is a trial package used for learning.
Home-page: UNKNOWN
Author: Jayashree
Author-email: jayukudari@gmail.com
License: MIT
Platform: UNKNOWN
